[
  {
    "Name": "Nakiea Cook, MBA",
    "Business": "Accountant",
    "Address": "",
    "Contact": "info@nakieacook.com",
    "Website": "https://www.nakieacook.com/",
    "FB": "https://www.facebook.com/nakiea.adger"
  },
  {
    "Name": "Born Bread Chasers Clothing",
    "Business": "Apparel",
    "Address": "",
    "Contact": "",
    "Website": "",
    "FB": "https://www.facebook.com/Bornbreadchasers.Clo/"
  },
  {
    "Name": "Cointel",
    "Business": "Apparel",
    "Address": "",
    "Contact": "",
    "Website": "https://historydipped.com/collections",
    "FB": "https://www.instagram.com/cointel/"
  },
  {
    "Name": "Everyday Poetry Boutique",
    "Business": "Apparel",
    "Address": "",
    "Contact": "(716) 429-5173",
    "Website": "https://everydaypoetryboutique.com/",
    "FB": "https://www.facebook.com/everydaypoetryboutique/"
  },
  {
    "Name": "GUAGGI",
    "Business": "Apparel",
    "Address": "",
    "Contact": "",
    "Website": "https://www.guaggi.com/",
    "FB": "https://www.facebook.com/guaggi/"
  },
  {
    "Name": "LVSH",
    "Business": "Apparel",
    "Address": "",
    "Contact": "",
    "Website": "https://www.lvshclothing.com/",
    "FB": "https://www.facebook.com/LvshClothing/"
  },
  {
    "Name": "TrapNerd Creations",
    "Business": "Apparel",
    "Address": "",
    "Contact": "",
    "Website": "https://www.trapnerdcreations.com/",
    "FB": "https://www.facebook.com/TrapNerdCreations/"
  },
  {
    "Name": "Ashley Kay",
    "Business": "Art",
    "Address": "",
    "Contact": "",
    "Website": "https://www.instagram.com/art_ashleykay/",
    "FB": ""
  },
  {
    "Name": "Brandie Chicole",
    "Business": "Art",
    "Address": "",
    "Contact": "",
    "Website": "https://www.instagram.com/artbyb._/",
    "FB": ""
  },
  {
    "Name": "By Edreys",
    "Business": "Art",
    "Address": "",
    "Contact": "",
    "Website": "https://edreys.com/",
    "FB": "https://www.facebook.com/byEdreys/"
  },
  {
    "Name": "The Jalen Law Collection",
    "Business": "Art",
    "Address": "",
    "Contact": "",
    "Website": "http://thejalenlawcollection.com/",
    "FB": "https://www.facebook.com/TheJalenLawCollection/"
  },
  {
    "Name": "The Knotty Buffalo",
    "Business": "Arts & Crafts Store",
    "Address": "",
    "Contact": "(716) 949-6204",
    "Website": "https://knottybuffalo.com/",
    "FB": "https://www.facebook.com/knottybuffalo716/"
  },
  {
    "Name": "Crystal J. Rodriguez, Esq.",
    "Business": "Attorney",
    "Address": "",
    "Contact": "(716) 416-1888",
    "Website": "https://crystalrodriguezesq.com/",
    "FB": "https://www.facebook.com/crystalclearesq/"
  },
  {
    "Name": "Main Hand Wash & Detail",
    "Business": "Auto Shop",
    "Address": "1712 Main St, Buffalo, NY 14209",
    "Contact": "(716) 885-2195",
    "Website": "https://main-handwash-detail.hub.biz/",
    "FB": "https://www.facebook.com/pages/Main-Handwash-Detail/162175203807747"
  },
  {
    "Name": "350 Sweets & Treats",
    "Business": "Bakery",
    "Address": "Stockbridge Ave, Buffalo, NY 14215",
    "Contact": "(716) 715-4789",
    "Website": "",
    "FB": "https://www.facebook.com/350SweetsTreats/"
  },
  {
    "Name": "Cake Crazy Bakery",
    "Business": "Bakery",
    "Address": "2525 William St Cheektowaga, New York 14206",
    "Contact": "(716) 235-8002",
    "Website": "http://www.cakecrazybakery.com/",
    "FB": "https://www.facebook.com/cakecrazybakery/"
  },
  {
    "Name": "Ravelle Culinary Creations, LLC",
    "Business": "Bakery",
    "Address": "37 Chandler Street, Buffalo, NY 14207",
    "Contact": "(716) 880-6545",
    "Website": "http://www.ravelleculinarycreations.com/",
    "FB": "https://www.facebook.com/ravelle.co/"
  },
  {
    "Name": "Shorty's Sweet Spot",
    "Business": "Bakery",
    "Address": "",
    "Contact": "(716) 430-7969",
    "Website": "",
    "FB": "https://www.facebook.com/BuffalosCheesecakeGoddess/"
  },
  {
    "Name": "Trice's Tasty Treats",
    "Business": "Bakery",
    "Address": "",
    "Contact": "(716) 288-2905",
    "Website": "https://www.instagram.com/trices_tastytreats/",
    "FB": "https://www.facebook.com/tricestastytreats/"
  },
  {
    "Name": "Balloon Obsession",
    "Business": "Balloons",
    "Address": "",
    "Contact": "",
    "Website": "https://balloonobsessionwny.com/",
    "FB": "https://www.facebook.com/BalloonObsession/"
  },
  {
    "Name": "Speak Easy",
    "Business": "Bar/Restaurant",
    "Address": "1194 E Lovejoy St, Buffalo, NY 14206",
    "Contact": "(716) 783-7477",
    "Website": "http://thespeakeasybuffalo.com/",
    "FB": "https://www.facebook.com/SpeakEasyBuffalo"
  },
  {
    "Name": "Cove & Mill Barbering Co",
    "Business": "Barbershop",
    "Address": "50 Elk St. Suite 120, Buffalo, NY 14210",
    "Contact": "(716) 625-2683",
    "Website": "https://coveandmillbarbering.com/",
    "FB": "https://www.facebook.com/coveandmillbarbering/"
  },
  {
    "Name": "The Standard",
    "Business": "Barbershop",
    "Address": "76 Allen St, Buffalo, NY 14202",
    "Contact": "(716) 867-1214",
    "Website": "",
    "FB": "https://www.facebook.com/pages/The-Standard/2307820099547033"
  },
  {
    "Name": "Beauty Wish Galore",
    "Business": "Beauty",
    "Address": "",
    "Contact": "",
    "Website": "https://www.instagram.com/beautywishgalore/",
    "FB": ""
  },
  {
    "Name": "Double Dose Lashes",
    "Business": "Beauty",
    "Address": "",
    "Contact": "",
    "Website": "https://bookforchanelle.as.me/schedule.php",
    "FB": "https://www.instagram.com/doubledoselashes/"
  },
  {
    "Name": "Haus of Kula",
    "Business": "Beauty",
    "Address": "P.O. Box 1685 Buffalo, NY",
    "Contact": "",
    "Website": "https://hausofkula.com/",
    "FB": "https://www.facebook.com/hausofkula/"
  },
  {
    "Name": "Lashed Buffalo",
    "Business": "Beauty",
    "Address": "1695 Hertel Avenue, Buffalo, NY",
    "Contact": "(716) 909 8787",
    "Website": "https://www.lashedbuffalo.com/",
    "FB": "https://www.facebook.com/lashedbuffalobeauty/"
  },
  {
    "Name": "Luxury Beauty Co",
    "Business": "Beauty",
    "Address": "180 N. Bailey ave suite #2, Amherst, NY 14226",
    "Contact": "(716) 390-5552",
    "Website": "",
    "FB": "https://www.facebook.com/LuxuryBeautyCO/"
  },
  {
    "Name": "O'DARA",
    "Business": "Beauty",
    "Address": "",
    "Contact": "",
    "Website": "https://www.odaraisbeauty.com/",
    "FB": ""
  },
  {
    "Name": "Zandra Beauty",
    "Business": "Beauty",
    "Address": "255 Great Arrow Ave, Ste 208  Buffalo, NY 14207",
    "Contact": "(855) 592-6372",
    "Website": "https://zandrabeauty.com/",
    "FB": "https://www.facebook.com/zandrabeauty/"
  },
  {
    "Name": "Zawadi Books",
    "Business": "Book Store",
    "Address": "1382 Jefferson Ave, Buffalo, NY 14208",
    "Contact": "(716) 903-6740",
    "Website": "",
    "FB": "https://www.facebook.com/pages/category/Independent-Bookstore/Zawadi-Books-466887943377904/"
  },
  {
    "Name": "Black Monarchy",
    "Business": "Boutique",
    "Address": "527 W Utica St, Buffalo, NY 14213",
    "Contact": "(347) 508-5267",
    "Website": "https://www.blackmonarchy.com/",
    "FB": "https://www.facebook.com/BlackMonarchy/"
  },
  {
    "Name": "Eat Off Art",
    "Business": "Boutique",
    "Address": "",
    "Contact": "",
    "Website": "https://www.eatoffart.com/",
    "FB": "https://www.facebook.com/eatoffart/"
  },
  {
    "Name": "Fee Designz",
    "Business": "Boutique",
    "Address": "",
    "Contact": "(803) 290-5491",
    "Website": "https://fee-designz.myshopify.com/",
    "FB": "https://www.facebook.com/feedesignz/"
  },
  {
    "Name": "Global Villages",
    "Business": "Boutique",
    "Address": "242 Grant St, Buffalo, NY 14213",
    "Contact": "(716) 887-3889",
    "Website": "",
    "FB": "https://www.facebook.com/Global-Villages-417253704995597/"
  },
  {
    "Name": "Janie's Emporium",
    "Business": "Boutique",
    "Address": "2943 Delaware Ave, Kenmore, NY 14217",
    "Contact": "(716) 573-6456",
    "Website": "http://www.janiesemporium.com/home",
    "FB": "https://www.facebook.com/JaniesEmporium/"
  },
  {
    "Name": "MMW Style Studio",
    "Business": "Boutique",
    "Address": "403 Main Street #108 Buffalo, New York 14203",
    "Contact": "(716) 812-0937",
    "Website": "http://www.mmwstylestudio.com/",
    "FB": "https://www.facebook.com/MMWStyleStudioLLC/"
  },
  {
    "Name": "MS Eye Candy",
    "Business": "Boutique",
    "Address": "85 Allen St. Buffalo, New York 14202",
    "Contact": "(716) 240-9961",
    "Website": "",
    "FB": "https://www.facebook.com/mseyecandybuffalo/"
  },
  {
    "Name": "Scents & Sensuality by Shajuan",
    "Business": "Boutique",
    "Address": "3281 Delaware Avenue, Buffalo, NY 14217",
    "Contact": "(716) 424-0024",
    "Website": "https://scentsandsensualitybyshajuan.com/",
    "FB": "https://www.facebook.com/Scents-Sensuality-By-Shajuan-612131012475577/"
  },
  {
    "Name": "The Cellar Boutique",
    "Business": "Boutique",
    "Address": "569 Elmwood Ave Buffalo, New York 14222",
    "Contact": "(716) 783-9161",
    "Website": "https://www.thexcellar.us/",
    "FB": "https://www.facebook.com/thexcellar/"
  },
  {
    "Name": "ASA Janitorial Services",
    "Business": "Cleaning Service",
    "Address": "790 Carl Street, Buffalo, NY 14215",
    "Contact": "(716) 313-3355",
    "Website": "http://www.asajanitorialsvcs.com/",
    "FB": "https://www.facebook.com/greenteam23/"
  },
  {
    "Name": "Heavenly Hands Commercial Cleaning",
    "Business": "Cleaning Service",
    "Address": "",
    "Contact": "(716) 953-3207",
    "Website": "hhdevelopment@mail.com",
    "FB": ""
  },
  {
    "Name": "Mobile Eco Steam - Mobile Auto Detailing & Carpet Cleaning",
    "Business": "Cleaning Service",
    "Address": "",
    "Contact": "(716) 393-5553",
    "Website": "https://www.mobileecosteam.com/",
    "FB": "https://www.facebook.com/mobileecosteam/"
  },
  {
    "Name": "Im Livin B Apparel & Printing",
    "Business": "Clothing & Printing",
    "Address": "2931 Delaware Ave, Kenmore, NY 14217",
    "Contact": "(716) 436-5169",
    "Website": "http://www.imlivinb.com/",
    "FB": "https://www.facebook.com/ImLivinB/"
  },
  {
    "Name": "Golden Cup Coffee",
    "Business": "Coffee Shop",
    "Address": "1323 Jefferson Ave, Buffalo, NY 14208",
    "Contact": "(716) 883-7770",
    "Website": "https://goldencupcoffee.com/",
    "FB": "https://www.facebook.com/goldencupcoffee/"
  },
  {
    "Name": "African Heritage Food Co-Op",
    "Business": "Co-Op",
    "Address": "2616 Highland Ave Niagara Falls, NY 14305",
    "Contact": "(716) 573-1844",
    "Website": "https://myahfc.com/",
    "FB": "https://www.facebook.com/ahfcbuffalo/"
  },
  {
    "Name": "Black Door",
    "Business": "Creative Opportunities",
    "Address": "",
    "Contact": "",
    "Website": "https://www.opentheblackdoor.com/",
    "FB": "https://www.facebook.com/BlkDoor/"
  },
  {
    "Name": "By Your Side Credit",
    "Business": "Credit Repair",
    "Address": "",
    "Contact": "(716) 482-0643",
    "Website": "http://www.byscredit.com/",
    "FB": "https://www.facebook.com/Byscredit/"
  },
  {
    "Name": "Verve Dance Studio, Arts Education",
    "Business": "Dance Studio",
    "Address": "429 Plymouth Ave, Buffalo, NY 14213",
    "Contact": "",
    "Website": "http://vervedancestudio.com/",
    "FB": "https://www.facebook.com/VerveDanceStudio/"
  },
  {
    "Name": "Wood Dental",
    "Business": "Dentistry",
    "Address": "564 Franklin St, Buffalo, NY 14202",
    "Contact": "(716) 882-0800",
    "Website": "http://www.wooddental.com/",
    "FB": "https://www.facebook.com/pages/Wood-Dental-Associates/174550643759"
  },
  {
    "Name": "Calming Nature",
    "Business": "Doula",
    "Address": "223 Grant St. Buffalo, NY 14213",
    "Contact": "(716) 909-0074",
    "Website": "https://www.calmingnaturedoula.com/",
    "FB": ""
  },
  {
    "Name": "DJ Dre",
    "Business": "DJ",
    "Address": "",
    "Contact": "(716) 430-1033",
    "Website": "https://www.djdremusic.com/",
    "FB": "https://www.facebook.com/DjDreMusicandPhotoBooth/"
  },
  {
    "Name": "You In Mind Events",
    "Business": "Event Planning",
    "Address": "",
    "Contact": "(716) 833-0924",
    "Website": "https://www.youinmindevents.com/",
    "FB": "https://www.facebook.com/YouInMindEvents/"
  },
  {
    "Name": "Black Gem Space",
    "Business": "Fitness",
    "Address": "",
    "Contact": "",
    "Website": "https://www.instagram.com/blackgemspace/",
    "FB": ""
  },
  {
    "Name": "GCOPE FIT",
    "Business": "Fitness",
    "Address": "3565 Sheridan Drive, Amherst, NY 14226",
    "Contact": "(716) 218-8011",
    "Website": "https://gcopefitness.com/",
    "FB": "https://www.facebook.com/GCopeFitness/"
  },
  {
    "Name": "GoPole Fitness",
    "Business": "Fitness",
    "Address": "30 Essex Suite C, Buffalo, NY 14214",
    "Contact": "(716) 235-1348",
    "Website": "https://www.gopolefit.com/",
    "FB": "https://www.facebook.com/gopolefitness/"
  },
  {
    "Name": "Macfitness Shed 2.0",
    "Business": "Fitness",
    "Address": "",
    "Contact": "(716) 218-8011",
    "Website": "https://macfitnessshed20.com/",
    "FB": "https://www.facebook.com/macfitness.facility"
  },
  {
    "Name": "Miss Body Language Fitness",
    "Business": "Fitness",
    "Address": "",
    "Contact": "",
    "Website": "https://linktr.ee/missbodylanguage",
    "FB": "https://www.instagram.com/missbodylanguagefit/"
  },
  {
    "Name": "Ousmane Camara",
    "Business": "Financial Advisor",
    "Address": "",
    "Contact": "",
    "Website": "https://www.linkedin.com/in/ousmane-camara-002559167/",
    "FB": ""
  },
  {
    "Name": "Feed Buffalo",
    "Business": "Food Pantry",
    "Address": "456 Massachusetts Ave Buffalo, NY 14213",
    "Contact": "(716) 588-0137",
    "Website": "https://www.feedbuffalo.org/",
    "FB": "https://www.facebook.com/feedbuffalo"
  },
  {
    "Name": "Mad Sauces Food Truck",
    "Business": "Food Truck",
    "Address": "",
    "Contact": "(716) 218-8810",
    "Website": "https://madsauces716.com/",
    "FB": "https://www.facebook.com/Madsauces/"
  },
  {
    "Name": "The Flaming Fish",
    "Business": "Food Truck",
    "Address": "",
    "Contact": "(716) 279-9725",
    "Website": "http://www.theflamingfish.com/",
    "FB": "https://www.facebook.com/FlamingFishTruck/"
  },
  {
    "Name": "T. L. Pickens Funeral Home",
    "Business": "Funeral Home",
    "Address": "66 E Utica Street, Buffalo, NY 14209",
    "Contact": "(716) 893-0084",
    "Website": "https://www.tonylpickens.com/",
    "FB": ""
  },
  {
    "Name": "BJB Multimedia",
    "Business": "Graphic Designer",
    "Address": "",
    "Contact": "info@bjbmultimedia.com",
    "Website": "https://www.bjbmultimedia.com/",
    "FB": "https://www.facebook.com/bjbmultimedia"
  },
  {
    "Name": "Glory Market",
    "Business": "Grocery",
    "Address": "472 Elmwood Avenue Buffalo, NY 14222",
    "Contact": "(716) 710-8370",
    "Website": "",
    "FB": "https://www.facebook.com/glorymarketllc/"
  },
  {
    "Name": "Caregiver Concierge Services",
    "Business": "Healthcare Navigation",
    "Address": "",
    "Contact": "(716) 348-4220",
    "Website": "",
    "FB": "https://www.facebook.com/CaregiverConciergeServices/"
  },
  {
    "Name": "Chocolate Bar Hair",
    "Business": "Hair Salon",
    "Address": "1132 Kensington ave, Buffalo, NY 14215",
    "Contact": "(716) 597-2959",
    "Website": "https://www.chocolatebarhair.com/",
    "FB": "https://www.facebook.com/chocolatebarhair/"
  },
  {
    "Name": "Merchant Logo Head Quarters Design Studio",
    "Business": "Hair Salon",
    "Address": "1016 Kensington Ave #5, Buffalo, NY 14215",
    "Contact": "(716) 832-0300",
    "Website": "https://www.head25.com/",
    "FB": "https://www.facebook.com/pages/Head-Quarters-Design-Studio/972651462756335"
  },
  {
    "Name": "The Hair Hive",
    "Business": "Hair Salon",
    "Address": "1413 Fillmore Avenue, Buffalo, NY 14211",
    "Contact": "(716) 427-8830",
    "Website": "https://www.thhbuffalo.com/",
    "FB": "https://www.facebook.com/The-Hair-Hive-107785880572717"
  },
  {
    "Name": "The Loc Room",
    "Business": "Hair Salon",
    "Address": "1012 Kensington Ave, Buffalo, NY 14215",
    "Contact": "(716) 246-4542",
    "Website": "https://thelocroom.com/",
    "FB": "https://www.facebook.com/thelocroom/"
  },
  {
    "Name": "Brahma Body Butter",
    "Business": "Holistic Skincare",
    "Address": "",
    "Contact": "(716) 436-9793",
    "Website": "https://www.etsy.com/shop/BrahmaBodyButter",
    "FB": "https://www.facebook.com/BodyButter716/"
  },
  {
    "Name": "Clinton Hawkins - Pillar To Post Home Inspectors",
    "Business": "Home Inspector",
    "Address": "303 Meyer Rd, West Seneca, NY 14224",
    "Contact": "(716) 608-6829",
    "Website": "https://clintonhawkins.pillartopost.com/",
    "FB": "https://www.facebook.com/clintonhawkinsP2P/"
  },
  {
    "Name": "Blues Home Repair",
    "Business": "Home Repair",
    "Address": "",
    "Contact": "(716) 427-6900",
    "Website": "https://blueshomerepairsllc.com/",
    "FB": "https://www.facebook.com/Blues-Home-Repair-LLC-183906935343705/"
  },
  {
    "Name": "Elle James",
    "Business": "Interior Design",
    "Address": "",
    "Contact": "(202) 520-4436",
    "Website": "https://www.ellejamesinteriors.com/",
    "FB": "https://www.facebook.com/ElleJamesInteriors/"
  },
  {
    "Name": "Honey Sweet Jam LLC",
    "Business": "Jam",
    "Address": "PO Box 546, Kenmore, NY 14217",
    "Contact": "honeysweetjamllc@gmail.com",
    "Website": "https://www.instagram.com/honeysweetjam/",
    "FB": ""
  },
  {
    "Name": "Franci Jewelry",
    "Business": "Jewelry",
    "Address": "",
    "Contact": "",
    "Website": "https://www.francibynicoledavis.com/",
    "FB": "https://www.facebook.com/Franci-Jewelry-293192271408927/"
  },
  {
    "Name": "Do It 4 Us Landscaping",
    "Business": "Landscaping",
    "Address": "",
    "Contact": "(716) 936-0620",
    "Website": "https://doit4uslandscaping.com/",
    "FB": "https://www.facebook.com/Doit4uslandscaping/"
  },
  {
    "Name": "LAST Call Laundry Services",
    "Business": "Laundry",
    "Address": "990 Kenmore Ave Suite A, Buffalo, NY 14216",
    "Contact": "(716) 541-1106",
    "Website": "http://lastcalllaundry.com/",
    "FB": "https://www.facebook.com/lastcalllaundry/"
  },
  {
    "Name": "Hertel Liquor Library",
    "Business": "Liquor Store",
    "Address": "1673 Hertel Avenue, Buffalo, NY 14216",
    "Contact": "(716) 768-3669",
    "Website": "http://www.hertelliquorlibrary.com/",
    "FB": "https://www.facebook.com/hertelliquorlibrary/"
  },
  {
    "Name": "International Wine & Spirits",
    "Business": "Liquor Store",
    "Address": "2580 Main St, Buffalo, NY 14214",
    "Contact": "(716) 837-5607",
    "Website": "http://www.buffaloliquorstore.com/",
    "FB": "https://www.facebook.com/IWSBuffaloNY/posts/10157382245392838"
  },
  {
    "Name": "L C & J Liquors",
    "Business": "Liquor Store",
    "Address": "2034 Genesee St, Buffalo, NY 14211",
    "Contact": "(716) 897-5194",
    "Website": "",
    "FB": "https://www.facebook.com/LCJLiquors/"
  },
  {
    "Name": "The Groove Lounge",
    "Business": "Lounge",
    "Address": "1210 Broadway, Buffalo, NY 14212",
    "Contact": "(716) 939-3149",
    "Website": "",
    "FB": ""
  },
  {
    "Name": "Enchanted Faces",
    "Business": "Makeup Artist",
    "Address": "",
    "Contact": "(716) 812-9477",
    "Website": "https://www.youtube.com/user/Channy729",
    "FB": "https://www.facebook.com/enchantedfaces17/"
  },
  {
    "Name": "Makeup by Mani",
    "Business": "Makeup Artist",
    "Address": "",
    "Contact": "",
    "Website": "https://linktr.ee/Makeupbymani24",
    "FB": "https://www.instagram.com/makeupbymani24/"
  },
  {
    "Name": "OakRight Experience",
    "Business": "Marketing (Social Media)",
    "Address": "",
    "Contact": "(716) 908-5641",
    "Website": "",
    "FB": ""
  },
  {
    "Name": "Alls Good Eats",
    "Business": "Meal Prep",
    "Address": "",
    "Contact": "",
    "Website": "https://www.instagram.com/allsgoodeats/",
    "FB": ""
  },
  {
    "Name": "Core Cuisine Meal Solutions",
    "Business": "Meal Prep",
    "Address": "37 Chandler Street, Buffalo, NY 14207",
    "Contact": "(716) 880-6545",
    "Website": "http://www.ravelleculinarycreations.com/",
    "FB": "https://www.facebook.com/corecuisine/"
  },
  {
    "Name": "Munchie Manz",
    "Business": "Meal Prep",
    "Address": "",
    "Contact": "(716) 316-0726",
    "Website": "https://www.munchiemanz.com/",
    "FB": "https://www.facebook.com/MunchieManz/"
  },
  {
    "Name": "WNY Merchant Consulting",
    "Business": "Merchant Consulting",
    "Address": "",
    "Contact": "(716) 817-0088",
    "Website": "",
    "FB": "https://www.facebook.com/rgwnymc/"
  },
  {
    "Name": "Dazzling Beauty Nail Slon",
    "Business": "Nail Salon",
    "Address": "2437 Delaware Ave Buffalo, New York 14216",
    "Contact": "(716) 322-6805",
    "Website": "https://www.dazzlingbeautynails.com/",
    "FB": "https://www.facebook.com/Dazzlingbeautybydom/"
  },
  {
    "Name": "Envious Beauty Bar",
    "Business": "Nail Salon",
    "Address": "",
    "Contact": "",
    "Website": "https://enviousbeautybar.as.me/schedule.php",
    "FB": "https://www.instagram.com/queentns/"
  },
  {
    "Name": "Top Coat Nail Lounge",
    "Business": "Nail Salon",
    "Address": "416 West Ferry Street, Buffalo, NY 14213",
    "Contact": "(716) 262-0303",
    "Website": "https://www.topcoatnl.com/",
    "FB": "https://www.facebook.com/TopCoatNailLounge/"
  },
  {
    "Name": "Pampered Paws n' Play",
    "Business": "Pet Care",
    "Address": "1840 Maple Rd, Amherst, NY, 14221",
    "Contact": "(716) 281-0310",
    "Website": "https://pamperedpawsnplay.com/",
    "FB": "https://www.facebook.com/pamperedpawsnplay/"
  },
  {
    "Name": "Alford's Angels",
    "Business": "Pet Grooming",
    "Address": "1141 Kenmore Ave, Buffalo NY, 14217",
    "Contact": "(716) 249-2114",
    "Website": "https://www.alfordsangels.com/",
    "FB": "https://www.facebook.com/AlfordsAngelsDogGroomingAndBeauty/"
  },
  {
    "Name": "Alana Adetola Arts",
    "Business": "Photographer",
    "Address": "",
    "Contact": "",
    "Website": "https://www.alanadetolartsphotography.com/",
    "FB": "https://www.facebook.com/alanadetolartsphotographyllc/"
  },
  {
    "Name": "Addo Productions",
    "Business": "Photophy/Videography",
    "Address": "",
    "Contact": "(415) 374-9410",
    "Website": "https://www.addoproductions.com/",
    "FB": "https://www.facebook.com/addoproductions/"
  },
  {
    "Name": "AWR Studios",
    "Business": "Photophy/Videography",
    "Address": "",
    "Contact": "(716) 666-1460",
    "Website": "https://www.instagram.com/awrstudios/",
    "FB": "https://www.facebook.com/AWRbooking/"
  },
  {
    "Name": "What's Pop-In",
    "Business": "Popcorn",
    "Address": "418 W Ferry St, Buffalo, NY 14213",
    "Contact": "",
    "Website": "https://www.whatspoppingourmetpopcorn.com/",
    "FB": ""
  },
  {
    "Name": "Get Fokus'd Productions",
    "Business": "Production Company",
    "Address": "",
    "Contact": "(716) 427-4386",
    "Website": "https://www.getfokusdproductions.com/",
    "FB": "https://www.facebook.com/GetFokusdProductions/"
  },
  {
    "Name": "Latrice \"Lari\" Everett",
    "Business": "Real Estate",
    "Address": "",
    "Contact": "(585) 297-0536",
    "Website": "https://leverett.mjpeterson.com/",
    "FB": ""
  },
  {
    "Name": "At Eleven Wings",
    "Business": "Restaurant",
    "Address": "3225 Main St Buffalo, New York 14214",
    "Contact": "(716) 899-2011",
    "Website": "",
    "FB": "https://www.facebook.com/atelevenwingsandcuisines/"
  },
  {
    "Name": "Brothers Takeout Cafe & Catering",
    "Business": "Restaurant",
    "Address": "1281 Hertel Ave Buffalo, NY 14216",
    "Contact": "(716) 322-0084",
    "Website": "https://716brothers.com/",
    "FB": "https://www.facebook.com/716brothers/"
  },
  {
    "Name": "Buffalo Soul",
    "Business": "Restaurant",
    "Address": "454 Pearl St Buffalo, New York 14202",
    "Contact": "(716) 768-8549",
    "Website": "https://buffalosoulny.com/",
    "FB": "https://www.facebook.com/buffalosoulcatering/?hc_location=ufi"
  },
  {
    "Name": "Caribbean Flava",
    "Business": "Restaurant",
    "Address": "630 10th Street, Niagara Falls 14301",
    "Contact": "(716) 423-9995",
    "Website": "",
    "FB": "https://www.facebook.com/CaribbeanFlavaNY/"
  },
  {
    "Name": "Caribbean Experience",
    "Business": "Restaurant",
    "Address": "2897 Bailey Ave, Buffalo, NY 14215",
    "Contact": "(716) 838-5131",
    "Website": "",
    "FB": ""
  },
  {
    "Name": "Em Tea Coffee",
    "Business": "Restaurant",
    "Address": "80 Oakgrove Avenue Buffalo, New York",
    "Contact": "(716) 884-1444",
    "Website": "http://www.emteacoffeecup.com/",
    "FB": "https://www.facebook.com/Em-Tea-Coffeecup-Cafe-115576138467893/"
  },
  {
    "Name": "Freddy J's BBQ",
    "Business": "Restaurant",
    "Address": "195 Grant St, Buffalo, NY 14213",
    "Contact": "(716) 424-2926",
    "Website": "",
    "FB": "https://www.facebook.com/freddyjsongrant/"
  },
  {
    "Name": "G&B Fish, Shrimp and Chicken",
    "Business": "Restaurant",
    "Address": "1532 Genesee Street Buffalo, NY 14211",
    "Contact": "(716) 331-3485",
    "Website": "https://gandbfishshrimpandchicken.com/menu",
    "FB": ""
  },
  {
    "Name": "Ikes & BG's Restaurant",
    "Business": "Restaurant",
    "Address": "1646 Genesee St, Buffalo, NY 14211",
    "Contact": "(716) 892-4301",
    "Website": "https://ikeandbgsrestaurant.com/",
    "FB": "https://www.facebook.com/pages/category/Barbecue-Restaurant/IKE-BGS-Restuarant-756226574565144/"
  },
  {
    "Name": "Island Mix Restaurant",
    "Business": "Restaurant",
    "Address": "883 Jefferson Ave, Buffalo, NY 14204",
    "Contact": "(716) 380-9115",
    "Website": "",
    "FB": "https://www.facebook.com/pages/Island-Mix-Restaurant/1442767192467539"
  },
  {
    "Name": "Je Ne Sais Quoi",
    "Business": "Restaurant",
    "Address": "1673 & 1633 Hertel Ave Buffalo, NY 14216",
    "Contact": "(716) 440-1065",
    "Website": "https://www.jenesaisquoibuffalo.com",
    "FB": "https://www.facebook.com/pages/category/Soul-Food-Restaurant/Je-Ne-Sais-Quoi-Taste-Like-Something-805980702840452/"
  },
  {
    "Name": "Kalypso Restaurant",
    "Business": "Restaurant",
    "Address": "12 Winspear Ave, Buffalo, NY 14214",
    "Contact": "(716) 834-3663",
    "Website": "",
    "FB": "https://www.facebook.com/KalypsoRestaurant/"
  },
  {
    "Name": "La Verdad Cafe",
    "Business": "Restaurant",
    "Address": "1132 East Lovejoy, Buffalo, NY 14206",
    "Contact": "(716) 768-3150",
    "Website": "",
    "FB": "https://www.facebook.com/MudfootJonesSr/"
  },
  {
    "Name": "Lee's Barbecue",
    "Business": "Restaurant",
    "Address": "1269 Fillmore Ave, Buffalo, NY 14211",
    "Contact": "(716) 896-8887",
    "Website": "",
    "FB": "https://www.facebook.com/pages/Lees-Barbecue/115100655174684"
  },
  {
    "Name": "Ms. Goodies",
    "Business": "Restaurant",
    "Address": "1836 Bailey Ave, Buffalo, NY 14211",
    "Contact": "(716) 936-3690",
    "Website": "",
    "FB": "https://www.facebook.com/ms.goodiesjunkyarddog/"
  },
  {
    "Name": "PhatCatz of WNY, Inc",
    "Business": "Restaurant",
    "Address": "965 Kensington Ave, Buffalo, NY 14215",
    "Contact": "(716) 235-8549",
    "Website": "",
    "FB": "https://www.facebook.com/phatcatzofwnyinc/"
  },
  {
    "Name": "Pine Hill Halal Market",
    "Business": "Restaurant",
    "Address": "286 Genesee St, Buffalo, NY 14225",
    "Contact": "(716) 597-0002",
    "Website": "",
    "FB": ""
  },
  {
    "Name": "Shy's Original Steak House",
    "Business": "Restaurant",
    "Address": "690 Fillmore Ave, Buffalo, NY 14212",
    "Contact": "(716) 852-7497",
    "Website": "",
    "FB": "https://www.facebook.com/ShysSteakhouse/"
  },
  {
    "Name": "Sunshine Vegan Eats",
    "Business": "Restaurant",
    "Address": "893 Jefferson Ave, Buffalo, NY 14204-1102",
    "Contact": "(716) 725-0284",
    "Website": "https://www.sunshineveganeats.com/",
    "FB": "https://www.facebook.com/SunshineVeganEats/"
  },
  {
    "Name": "The Oakk Room",
    "Business": "Restaurant",
    "Address": "1435 Main St, Buffalo, NY 14209",
    "Contact": "(716) 771-2773",
    "Website": "https://www.theoakkroom.com/",
    "FB": "https://www.facebook.com/TheOakkroom/"
  },
  {
    "Name": "The Traphaus",
    "Business": "Restaurant",
    "Address": "",
    "Contact": "(716) 322-5696",
    "Website": "",
    "FB": "https://www.facebook.com/traphauscatering/"
  },
  {
    "Name": "WING KINGS 716",
    "Business": "Restaurant",
    "Address": "484 Elmwood Ave Buffalo, New York 14222",
    "Contact": "(716) 248-1427",
    "Website": "",
    "FB": "https://www.facebook.com/WINGKINGS716/"
  },
  {
    "Name": "Agorie Headwear",
    "Business": "Retail",
    "Address": "1434 Hertel Avenue, Buffalo, NY 14216",
    "Contact": "(716) 834-4287",
    "Website": "http://www.agorieheadwear.com/",
    "FB": "https://www.facebook.com/agorieheadwear/"
  },
  {
    "Name": "Classic Knot",
    "Business": "Retail",
    "Address": "P.O. Box 556 ​Amherst, NY 14226",
    "Contact": "(716) 544-8840",
    "Website": "https://www.classicknot.com/",
    "FB": "https://www.facebook.com/classicknot"
  },
  {
    "Name": "Masaai Consignment Boutique",
    "Business": "Retail",
    "Address": "208 E Delavan Ave Buffalo, New York 14208-1225",
    "Contact": "(716) 322-5696",
    "Website": "",
    "FB": "https://www.facebook.com/maasaicb/"
  },
  {
    "Name": "Serene Candles by Mia",
    "Business": "Retail",
    "Address": "",
    "Contact": "",
    "Website": "",
    "FB": "https://www.facebook.com/serenecandlesbymia/"
  },
  {
    "Name": "The Ink Spot",
    "Business": "Retail",
    "Address": "1440 Jefferson Ave. Buffalo, NY 14208",
    "Contact": "(716) 881-7594",
    "Website": "",
    "FB": "https://www.facebook.com/The-Ink-Spot-258285857561522/"
  },
  {
    "Name": "B&C Home Care",
    "Business": "Senior Care",
    "Address": "6400 Sheridan Dr ste 116, Williamsville, Buffalo, NY 14221, USA",
    "Contact": "(716) 633-7400",
    "Website": "https://www.bncunited.com/",
    "FB": "https://www.facebook.com/bandcunited/"
  },
  {
    "Name": "Nubian Onyx",
    "Business": "Spa",
    "Address": "4219 Transit Rd, Williamsville, NY 14221",
    "Contact": "(716) 406-8276",
    "Website": "https://www.nubianonyx.com/",
    "FB": "https://www.facebook.com/NubianOnyx/"
  },
  {
    "Name": "Rejuvinex Spa",
    "Business": "Spa",
    "Address": "2750 Delaware Ave, Buffalo, NY 14217",
    "Contact": "(716) 877-2220",
    "Website": "http://rejuvinexspa.com/",
    "FB": "https://www.facebook.com/rejuvinexspa/"
  },
  {
    "Name": "SalleyNycole’s Skin & Beauty Boutique",
    "Business": "Skin & Beauty",
    "Address": "990 Kenmore Ave Buffalo NY 14216",
    "Contact": "(716) 226-8450",
    "Website": "https://www.styleseat.com/m/v/salleynycole",
    "FB": ""
  },
  {
    "Name": "Paint The Town",
    "Business": "Studio",
    "Address": "74 Allen St, Buffalo, NY 14202",
    "Contact": "(716) 241-1516",
    "Website": "http://paintthetown716.com/",
    "FB": "https://www.facebook.com/PainttheTown716/"
  },
  {
    "Name": "Annrhods Tailoring",
    "Business": "Tailoring",
    "Address": "3185 Bailey Ave, Buffalo, NY 14215",
    "Contact": "(716) 838-5633",
    "Website": "",
    "FB": ""
  },
  {
    "Name": "Good Form Fitness",
    "Business": "Trainer",
    "Address": "",
    "Contact": "(716) 446-3734",
    "Website": "https://square.site/book/6K09KZ3WA09QP/good-form-fitness",
    "FB": "https://www.instagram.com/_goodformfitness_/"
  },
  {
    "Name": "716 Towing & Roadside",
    "Business": "Towing",
    "Address": "",
    "Contact": "(716) 229-0412",
    "Website": "https://716towingandroadside.com/",
    "FB": "https://www.facebook.com/Towaholic1/"
  },
  {
    "Name": "The Wigtique",
    "Business": "Wigs",
    "Address": "",
    "Contact": "",
    "Website": "https://www.thewigtique.com/",
    "FB": ""
  },
  {
    "Name": "Mind Body Flow Yoga",
    "Business": "Yoga Studio",
    "Address": "9380 Transit Road East Amherst, NY 14051",
    "Contact": "(716) 218-3167",
    "Website": "https://mindbodyflowyoga.com/",
    "FB": ""
  }
]